scarx_api_client/Channel.py
scarx_api_client/__init__.py
scarx_api_client/proto/__init__.py
scarx_api_client/proto/grpc/__init__.py
scarx_api_client/proto/grpc/api/__init__.py
scarx_api_client/proto/grpc/api/v1/__init__.py
scarx_api_client-0.6.3.dist-info/METADATA
scarx_api_client-0.6.3.dist-info/WHEEL
scarx_api_client-0.6.3.dist-info/top_level.txt
scarx_api_client-0.6.3.dist-info/RECORD
