Metadata-Version: 2.1
Name: scarx_api_client
Version: 0.6.3
Summary: Client for Scarx API
Author: Scartz
Author-email: github@scarx.net
Requires-Dist: grpclib
Requires-Dist: betterproto ==2.0.0b6
Requires-Dist: pydantic
